odoo/addons/energy_communities/__init__.py
odoo/addons/energy_communities/__manifest__.py
odoo/addons/energy_communities/hooks.py
odoo/addons/energy_communities/utils.py
odoo/addons/energy_communities/client_map/__init__.py
odoo/addons/energy_communities/client_map/config.py
odoo/addons/energy_communities/client_map/resources/landing_cmplace.py
odoo/addons/energy_communities/components/__init__.py
odoo/addons/energy_communities/components/collections.py
odoo/addons/energy_communities/components/user_creator.py
odoo/addons/energy_communities/controllers/__init__.py
odoo/addons/energy_communities/controllers/controllers.py
odoo/addons/energy_communities/controllers/website_form_controllers.py
odoo/addons/energy_communities/data/auth_oauth_provider_data.xml
odoo/addons/energy_communities/data/community_maps_data.xml
odoo/addons/energy_communities/data/crm_lead_tag.xml
odoo/addons/energy_communities/data/energy_action.xml
odoo/addons/energy_communities/data/ir_cron.xml
odoo/addons/energy_communities/data/product_data.xml
odoo/addons/energy_communities/data/utm_data.xml
odoo/addons/energy_communities/demo/res_company_demo.xml
odoo/addons/energy_communities/demo/res_lang_demo.xml
odoo/addons/energy_communities/demo/res_partner_demo.xml
odoo/addons/energy_communities/demo/res_user_demo.xml
odoo/addons/energy_communities/i18n/ca_ES.po
odoo/addons/energy_communities/i18n/energy_communities.pot
odoo/addons/energy_communities/i18n/es.po
odoo/addons/energy_communities/i18n/eu_ES.po
odoo/addons/energy_communities/migrations/14.0.1.1.12/post-add-internal-user-role.py
odoo/addons/energy_communities/migrations/14.0.5.1.0/post-setup-multicompany-partner.py
odoo/addons/energy_communities/migrations/14.0.9.5.1/post-migrate-energy-crm-tags-to-energy-actions.py
odoo/addons/energy_communities/models/__init__.py
odoo/addons/energy_communities/models/account_move.py
odoo/addons/energy_communities/models/auth_oauth_provider.py
odoo/addons/energy_communities/models/cm_coordinates_mixin.py
odoo14_addon_energy_communities-14.0.9.5.2.dist-info/METADATA
odoo14_addon_energy_communities-14.0.9.5.2.dist-info/WHEEL
odoo14_addon_energy_communities-14.0.9.5.2.dist-info/top_level.txt
odoo14_addon_energy_communities-14.0.9.5.2.dist-info/RECORD
