Metadata-Version: 2.1
Name: odoo14-addon-energy-communities
Version: 14.0.9.5.2
Summary: Energy Community
Home-page: https://coopdevs.org
Author: Coopdevs Treball SCCL & Som Energia SCCL
License: AGPL-3
Classifier: Programming Language :: Python
Classifier: Framework :: Odoo
Classifier: Framework :: Odoo :: 14.0
Classifier: License :: OSI Approved :: GNU Affero General Public License v3
Requires-Python: >=3.6
Requires-Dist: odoo14-addon-account-banking-mandate >=14.0.1.2.0
Requires-Dist: odoo14-addon-account-lock-date-update ==14.0.2.0.1.dev10
Requires-Dist: odoo14-addon-account-multicompany-easy-creation ==14.0.1.0.1.dev2
Requires-Dist: odoo14-addon-account-payment-order ==14.0.1.11.0
Requires-Dist: odoo14-addon-account-reconciliation-widget ==14.0.2.0.2
Requires-Dist: odoo14-addon-auth-api-key ==14.0.2.2.1
Requires-Dist: odoo14-addon-auth-oidc ==14.0.1.0.3.dev1
Requires-Dist: odoo14-addon-base-rest ==14.0.4.8.1
Requires-Dist: odoo14-addon-base-technical-features ==14.0.1.1.2.dev1
Requires-Dist: odoo14-addon-base-user-role-company ==14.0.2.0.2
Requires-Dist: odoo14-addon-base-user-role ==14.0.2.5.1
Requires-Dist: odoo14-addon-community-maps ==14.0.0.2.8
Requires-Dist: odoo14-addon-l10n-es-aeat-sii-oca ==14.0.2.10.2
Requires-Dist: odoo14-addon-l10n-es-aeat
Requires-Dist: odoo14-addon-mail-multicompany ==14.0.0.1.1.dev2
Requires-Dist: odoo14-addon-metadata ==14.0.0.0.1
Requires-Dist: odoo14-addon-partner-firstname >=14.0.1.1.1.dev4
Requires-Dist: odoo14-addon-partner-multi-company ==14.0.1.0.1.dev4
Requires-Dist: odoo14-addon-queue-job ==14.0.3.1.5
Requires-Dist: odoo <14.1dev,>=14.0a
